setup.py
PyOS/__init__.py
PyOS/core/OS.py
PyOS/core/__init__.py
PythonOS.egg-info/PKG-INFO
PythonOS.egg-info/SOURCES.txt
PythonOS.egg-info/dependency_links.txt
PythonOS.egg-info/top_level.txt