Metadata-Version: 1.0
Name: PythonOS
Version: 0.1.6
Summary: A simple OS package that can be used to build a Python OS.
Home-page: UNKNOWN
Author: Eric
Author-email: email@devwatch.epizy.com
License: MIT
Keywords: PythonOS
Platform: UNKNOWN
